{"v":3,"stories":{"configure-your-project--docs":{"id":"configure-your-project--docs","title":"Configure your project","name":"Docs","importPath":"./src/stories/Configure.mdx","storiesImports":[],"tags":["unattached-mdx","docs"],"kind":"Configure your project","story":"Docs","parameters":{"__id":"configure-your-project--docs","docsOnly":true,"fileName":"./src/stories/Configure.mdx"}},"example-button--docs":{"id":"example-button--docs","title":"Example/Button","name":"Docs","importPath":"./src/stories/Button.stories.tsx","tags":["autodocs","docs"],"storiesImports":[],"kind":"Example/Button","story":"Docs","parameters":{"__id":"example-button--docs","docsOnly":true,"fileName":"./src/stories/Button.stories.tsx"}},"example-button--primary":{"id":"example-button--primary","name":"Primary","title":"Example/Button","importPath":"./src/stories/Button.stories.tsx","tags":["autodocs","story"],"kind":"Example/Button","story":"Primary","parameters":{"__id":"example-button--primary","docsOnly":false,"fileName":"./src/stories/Button.stories.tsx"}},"example-button--outlined":{"id":"example-button--outlined","name":"Outlined","title":"Example/Button","importPath":"./src/stories/Button.stories.tsx","tags":["autodocs","story"],"kind":"Example/Button","story":"Outlined","parameters":{"__id":"example-button--outlined","docsOnly":false,"fileName":"./src/stories/Button.stories.tsx"}},"example-button--disabled":{"id":"example-button--disabled","name":"Disabled","title":"Example/Button","importPath":"./src/stories/Button.stories.tsx","tags":["autodocs","story"],"kind":"Example/Button","story":"Disabled","parameters":{"__id":"example-button--disabled","docsOnly":false,"fileName":"./src/stories/Button.stories.tsx"}},"example-button--small":{"id":"example-button--small","name":"Small","title":"Example/Button","importPath":"./src/stories/Button.stories.tsx","tags":["autodocs","story"],"kind":"Example/Button","story":"Small","parameters":{"__id":"example-button--small","docsOnly":false,"fileName":"./src/stories/Button.stories.tsx"}},"example-button--medium":{"id":"example-button--medium","name":"Medium","title":"Example/Button","importPath":"./src/stories/Button.stories.tsx","tags":["autodocs","story"],"kind":"Example/Button","story":"Medium","parameters":{"__id":"example-button--medium","docsOnly":false,"fileName":"./src/stories/Button.stories.tsx"}},"example-button--large":{"id":"example-button--large","name":"Large","title":"Example/Button","importPath":"./src/stories/Button.stories.tsx","tags":["autodocs","story"],"kind":"Example/Button","story":"Large","parameters":{"__id":"example-button--large","docsOnly":false,"fileName":"./src/stories/Button.stories.tsx"}},"example-popover--docs":{"id":"example-popover--docs","title":"Example/Popover","name":"Docs","importPath":"./src/stories/Popover.stories.tsx","tags":["autodocs","docs"],"storiesImports":[],"kind":"Example/Popover","story":"Docs","parameters":{"__id":"example-popover--docs","docsOnly":true,"fileName":"./src/stories/Popover.stories.tsx"}},"example-popover--primary":{"id":"example-popover--primary","name":"Primary","title":"Example/Popover","importPath":"./src/stories/Popover.stories.tsx","tags":["autodocs","story"],"kind":"Example/Popover","story":"Primary","parameters":{"__id":"example-popover--primary","docsOnly":false,"fileName":"./src/stories/Popover.stories.tsx"}},"example-select--docs":{"id":"example-select--docs","title":"Example/Select","name":"Docs","importPath":"./src/stories/Select.stories.tsx","tags":["autodocs","docs"],"storiesImports":[],"kind":"Example/Select","story":"Docs","parameters":{"__id":"example-select--docs","docsOnly":true,"fileName":"./src/stories/Select.stories.tsx"}},"example-select--primary":{"id":"example-select--primary","name":"Primary","title":"Example/Select","importPath":"./src/stories/Select.stories.tsx","tags":["autodocs","story"],"kind":"Example/Select","story":"Primary","parameters":{"__id":"example-select--primary","docsOnly":false,"fileName":"./src/stories/Select.stories.tsx"}},"example-tag--docs":{"id":"example-tag--docs","title":"Example/Tag","name":"Docs","importPath":"./src/stories/Tag.stories.tsx","tags":["autodocs","docs"],"storiesImports":[],"kind":"Example/Tag","story":"Docs","parameters":{"__id":"example-tag--docs","docsOnly":true,"fileName":"./src/stories/Tag.stories.tsx"}},"example-tag--primary":{"id":"example-tag--primary","name":"Primary","title":"Example/Tag","importPath":"./src/stories/Tag.stories.tsx","tags":["autodocs","story"],"kind":"Example/Tag","story":"Primary","parameters":{"__id":"example-tag--primary","docsOnly":false,"fileName":"./src/stories/Tag.stories.tsx"}},"example-tag--colors":{"id":"example-tag--colors","name":"Colors","title":"Example/Tag","importPath":"./src/stories/Tag.stories.tsx","tags":["autodocs","story"],"kind":"Example/Tag","story":"Colors","parameters":{"__id":"example-tag--colors","docsOnly":false,"fileName":"./src/stories/Tag.stories.tsx"}},"example-tag--sizes":{"id":"example-tag--sizes","name":"Sizes","title":"Example/Tag","importPath":"./src/stories/Tag.stories.tsx","tags":["autodocs","story"],"kind":"Example/Tag","story":"Sizes","parameters":{"__id":"example-tag--sizes","docsOnly":false,"fileName":"./src/stories/Tag.stories.tsx"}},"example-text--docs":{"id":"example-text--docs","title":"Example/Text","name":"Docs","importPath":"./src/stories/Text.stories.tsx","tags":["autodocs","docs"],"storiesImports":[],"kind":"Example/Text","story":"Docs","parameters":{"__id":"example-text--docs","docsOnly":true,"fileName":"./src/stories/Text.stories.tsx"}},"example-text--primary":{"id":"example-text--primary","name":"Primary","title":"Example/Text","importPath":"./src/stories/Text.stories.tsx","tags":["autodocs","story"],"kind":"Example/Text","story":"Primary","parameters":{"__id":"example-text--primary","docsOnly":false,"fileName":"./src/stories/Text.stories.tsx"}}}}
